AppiumFlutterLibrary/__init__.py
AppiumFlutterLibrary/version.py
AppiumFlutterLibrary/finder/__init__.py
AppiumFlutterLibrary/finder/elementfinder.py
AppiumFlutterLibrary/keywords/__init__.py
AppiumFlutterLibrary/keywords/_applicationmanagement.py
AppiumFlutterLibrary/keywords/_element.py
AppiumFlutterLibrary/keywords/_keyevents.py
AppiumFlutterLibrary/keywords/_logging.py
AppiumFlutterLibrary/keywords/_runonfailure.py
AppiumFlutterLibrary/keywords/_screen.py
AppiumFlutterLibrary/keywords/_touch.py
AppiumFlutterLibrary/keywords/_waiting.py
AppiumFlutterLibrary/keywords/keywordgroup.py
AppiumFlutterLibrary/utils/__init__.py
AppiumFlutterLibrary/utils/applicationcache.py
robotframework_appiumflutterlibrary-1.0.0.dist-info/LICENSE
robotframework_appiumflutterlibrary-1.0.0.dist-info/METADATA
robotframework_appiumflutterlibrary-1.0.0.dist-info/WHEEL
robotframework_appiumflutterlibrary-1.0.0.dist-info/top_level.txt
robotframework_appiumflutterlibrary-1.0.0.dist-info/RECORD
